gym_tl_tools/__init__.py
gym_tl_tools/automaton.py
gym_tl_tools/parser.py
gym_tl_tools/wrapper.py
gym_tl_tools-0.1.0.dist-info/METADATA
gym_tl_tools-0.1.0.dist-info/WHEEL
gym_tl_tools-0.1.0.dist-info/licenses/LICENSE
gym_tl_tools-0.1.0.dist-info/RECORD
