Metadata-Version: 2.4
Name: gym-tl-tools
Version: 0.1.0
Summary: Utilities to wrap gymnasium environments using TL rewards.
Project-URL: Homepage, https://miki-yuasa.github.io/gym-tl-tools
Project-URL: Repository, https://github.com/miki-yuasa/gym-tl-tools
Project-URL: Bug Tracker, https://github.com/miki-yuasa/gym-tl-tools/issues
Author-email: Mikihisa Yuasa <myuasa2@illinois.edu>
License: MIT
License-File: LICENSE
Classifier: Development Status :: 5 - Production/Stable
Classifier: Intended Audience :: Developers
Classifier: License :: OSI Approved :: MIT License
Classifier: Programming Language :: Python :: 3
Classifier: Programming Language :: Python :: 3.10
Classifier: Programming Language :: Python :: 3.11
Classifier: Programming Language :: Python :: 3.12
Classifier: Programming Language :: Python :: 3.13
Requires-Python: <3.14,>=3.10
Requires-Dist: gymnasium>=0.26
Requires-Dist: numpy>=1.21
Requires-Dist: pydantic<3.0,>=2.0
Requires-Dist: spottl<3.0,>=2.13
